blext/__init__.py
blext/__main__.py
blext/cli.py
blext/exceptions.py
blext/finders.py
blext/pack.py
blext/spec.py
blext/supported.py
blext/wheels.py
blext/blender_python/bl_init.py
blext-0.3.0.dist-info/METADATA
blext-0.3.0.dist-info/WHEEL
blext-0.3.0.dist-info/entry_points.txt
blext-0.3.0.dist-info/licenses/LICENSE
blext-0.3.0.dist-info/licenses/LICENSE_header.txt
blext-0.3.0.dist-info/RECORD
