Metadata-Version: 2.4
Name: blext
Version: 0.3.0
Summary: A fast, convenient project manager for Blender extensions.
Project-URL: Homepage, https://git.sofus.io/so-rose/blext
Author-email: Sofus Albert Høgsbro Rose <blext@sofusrose.com>
Maintainer-email: Sofus Albert Høgsbro Rose <blext@sofusrose.com>
License: AGPL-3.0-or-later
License-File: LICENSE
License-File: LICENSE_header.txt
Classifier: Development Status :: 3 - Alpha
Classifier: Environment :: Console
Classifier: Intended Audience :: Developers
Classifier: License :: OSI Approved :: GNU Affero General Public License v3 or later (AGPLv3+)
Classifier: Natural Language :: English
Classifier: Operating System :: OS Independent
Classifier: Programming Language :: Python :: 3
Classifier: Topic :: Artistic Software
Classifier: Topic :: Software Development :: Build Tools
Requires-Python: >=3.11
Requires-Dist: cyclopts>=3.1.5
Requires-Dist: pydantic>=2.10.5
Requires-Dist: pypdl>=1.5.1
Requires-Dist: rich>=13.9.4
Requires-Dist: tomli-w>=1.1.0
